easyshapey/__init__.py
easyshapey/core.py
easyshapey/selector.py
easyshapey-0.0.5.dist-info/METADATA
easyshapey-0.0.5.dist-info/WHEEL
easyshapey-0.0.5.dist-info/top_level.txt
easyshapey-0.0.5.dist-info/RECORD
