Metadata-Version: 2.4
Name: easyshapey
Version: 0.0.5
Summary:  package to draw boxes in 2d plots
Home-page: https://github.com/caganze/easyshapey
Author: caganze
Author-email: caganze@gmail.com
Classifier: Programming Language :: Python :: 3
Classifier: License :: OSI Approved :: MIT License
Classifier: Operating System :: OS Independent
Dynamic: author
Dynamic: author-email
Dynamic: classifier
Dynamic: description
Dynamic: description-content-type
Dynamic: home-page
Dynamic: summary
